amplifai/__init__.py
amplifai/amplifier.py
amplifai/examples.py
amplifai/prompt.py
amplifai/py.typed
amplifai-0.1.0.dist-info/licenses/LICENSE
amplifai-0.1.0.dist-info/METADATA
amplifai-0.1.0.dist-info/WHEEL
amplifai-0.1.0.dist-info/top_level.txt
amplifai-0.1.0.dist-info/RECORD
