Metadata-Version: 2.4
Name: amplifai
Version: 0.1.0
Summary: Amplifai is a package that allows you to transform your raw unstructured text into structured data in a few lines of codes.
Project-URL: Homepage, https://github.com/VianneyMI/amplifai
Requires-Python: >=3.10
License-File: LICENSE
Requires-Dist: langchain>=0.3.0
Requires-Dist: langchain-mistralai>=0.2.10
Requires-Dist: langchain-openai>=0.3.14
Requires-Dist: python-dotenv>=1.0.0
Dynamic: license-file
